[
  {
      "concept": "egoïstisch",
      "explanation": "zelfzuchtig, alleen aan jezelf denken"
  },
  {
      "concept": "geen blad voor de mond nemen",
      "explanation": "je eerlijke mening geven"
  },
  {
      "concept": "de lectuur",
      "explanation": "alles wat gelezen kan worden"
  },
  {
      "concept": "het rolmodel",
      "explanation": "iemand met een voorbeeldfunctie"
  },
  {
      "concept": "schijnheilig",
      "explanation": "als iemand zich braver en eerlijker voordoet dan hij of zij is"
  },
  {
      "concept": "vleien",
      "explanation": "complimenten geven die niet altijd gemeend zijn"
  },
  {
      "concept": "voorbeeldig",
      "explanation": "braaf, keurig"
  },
  {
      "concept": "voorschotelen",
      "explanation": "aanbieden"
  },
  {
      "concept": "vormend",
      "explanation": "iets wat belangrijk is voor iemands ontwikkeling"
  },
  {
      "concept": "de wildebras",
      "explanation": "levendig, wild kind"
  },
  {
      "concept": "accepteren",
      "explanation": "ermee akkoord gaan"
  },
  {
      "concept": "afschilderen",
      "explanation": "iemand op een bepaalde manier beschrijven"
  },
  {
      "concept": "bijdehand",
      "explanation": "snel en slim reageren"
  },
  {
      "concept": "lak hebben aan iets",
      "explanation": "het zich niet aantrekken"
  },
  {
      "concept": "onuitputtelijk",
      "explanation": "eindeloos"
  },
  {
      "concept": "pedagogisch",
      "explanation": "opvoedkundig"
  },
  {
      "concept": "het scala",
      "explanation": "een groot aantal"
  },
  {
      "concept": "universeel",
      "explanation": "algemeen geldend"
  },
  {
      "concept": "verstommen",
      "explanation": "sprakeloos worden"
  },
  {
      "concept": "vooruitstrevend",
      "explanation": "als je streeft naar vernieuwing"
  },
  {
      "concept": "aan de lopende band",
      "explanation": "aan één stuk door"
  },
  {
      "concept": "de criticus",
      "explanation": "iemand die iets beoordeelt, vaak negatief"
  },
  {
      "concept": "goedgemutst zijn",
      "explanation": "een goed humeur hebben, blij zijn"
  },
  {
      "concept": "de navolger",
      "explanation": "iemand die iets doet naar voorbeeld van een ander"
  },
  {
      "concept": "onfatsoenlijk",
      "explanation": "niet netjes"
  },
  {
      "concept": "de propaganda",
      "explanation": "reclame voor ideeën met als doel gedragsverandering"
  },
  {
      "concept": "rechtbreien",
      "explanation": "rechtzetten, herstellen"
  },
  {
      "concept": "sympathiek",
      "explanation": "aardig, vriendelijk"
  },
  {
      "concept": "tot inkeer komen",
      "explanation": "anders doen/denken omdat je beseft dat je fout deed/dacht"
  },
  {
      "concept": "veel stof doen opwaaien",
      "explanation": "opschudding veroorzaken"
  },
  {
      "concept": "argeloos",
      "explanation": "niet bewust van gevaar"
  },
  {
      "concept": "de epiloog",
      "explanation": "nawoord"
  },
  {
      "concept": "geforceerd",
      "explanation": "gemaakt, nep"
  },
  {
      "concept": "gegarandeerd",
      "explanation": "zeker, beslist"
  },
  {
      "concept": "iemand op het verkeerde been zetten",
      "explanation": "ergens een verkeerde indruk van geven"
  },
  {
      "concept": "het motief",
      "explanation": "reden waarom iemand iets doet"
  },
  {
      "concept": "onderscheppen",
      "explanation": "iemand op zijn weg tegenhouden"
  },
  {
      "concept": "schichtig",
      "explanation": "bang, schrikachtig"
  },
  {
      "concept": "het semester",
      "explanation": "periode van zes maanden, een halfjaar"
  },
  {
      "concept": "weergalmen",
      "explanation": "herhaling van een klank bij terugkaatsen van het geluid"
  }
]
